mini_postoffice/__init__.py
mini_postoffice/mini_postoffice.py
mini_postoffice-0.1.8.dist-info/LICENSE
mini_postoffice-0.1.8.dist-info/METADATA
mini_postoffice-0.1.8.dist-info/WHEEL
mini_postoffice-0.1.8.dist-info/top_level.txt
mini_postoffice-0.1.8.dist-info/RECORD
