Metadata-Version: 2.1
Name: mini-postoffice
Version: 0.1.8
Summary: small package for sending email
Home-page: https://github.com/jryzj/mini_postoffice
Author: Jerry Zang
Author-email: 2381002887@qq.com
License: MIT
Keywords: email smtp tool
Platform: UNKNOWN
Classifier: Intended Audience :: Developers
Classifier: License :: OSI Approved :: MIT License
Classifier: Programming Language :: Python :: 3
Classifier: Development Status :: 3 - Alpha
Requires-Python: >=3
Requires-Dist: chardet
